exonware/__init__.py
exonware-0.0.1.dist-info/METADATA
exonware-0.0.1.dist-info/WHEEL
exonware-0.0.1.dist-info/licenses/LICENSE
exonware-0.0.1.dist-info/RECORD
