Metadata-Version: 2.4
Name: exonware
Version: 0.0.1
Summary: eXonware - Complete Python ecosystem: xSystem, xNode, xData, xSchema, xAction, xEntity - Enterprise-grade libraries in one install
Project-URL: Homepage, https://github.com/exonware
Project-URL: Documentation, https://github.com/exonware/exonware
Project-URL: Repository, https://github.com/exonware/exonware.git
Project-URL: Issues, https://github.com/exonware/exonware/issues
Project-URL: Changelog, https://github.com/exonware/exonware/releases
Project-URL: Company, https://exonware.com
Author-email: "Eng. Muhammad AlShehri" <connect@exonware.com>
Maintainer-email: "Eng. Muhammad AlShehri" <connect@exonware.com>
License: MIT
License-File: LICENSE
Keywords: ecosystem,enterprise,exonware,framework,meta-package,xaction,xdata,xentity,xnode,xschema,xsystem
Classifier: Development Status :: 5 - Production/Stable
Classifier: Intended Audience :: Developers
Classifier: License :: OSI Approved :: MIT License
Classifier: Operating System :: OS Independent
Classifier: Programming Language :: Python :: 3
Classifier: Programming Language :: Python :: 3.8
Classifier: Programming Language :: Python :: 3.9
Classifier: Programming Language :: Python :: 3.10
Classifier: Programming Language :: Python :: 3.11
Classifier: Programming Language :: Python :: 3.12
Classifier: Topic :: Internet :: WWW/HTTP :: HTTP Servers
Classifier: Topic :: Security :: Cryptography
Classifier: Topic :: Software Development :: Libraries :: Python Modules
Classifier: Topic :: System :: Monitoring
Classifier: Topic :: System :: Systems Administration
Requires-Python: >=3.8
Requires-Dist: exonware-xaction>=0.0.1
Requires-Dist: exonware-xdata>=0.0.1
Requires-Dist: exonware-xentity>=0.0.1
Requires-Dist: exonware-xnode>=0.0.1
Requires-Dist: exonware-xschema>=0.0.1
Requires-Dist: exonware-xsystem>=0.0.1
Provides-Extra: dev
Requires-Dist: black>=23.0.0; extra == 'dev'
Requires-Dist: isort>=5.12.0; extra == 'dev'
Requires-Dist: mypy>=1.0.0; extra == 'dev'
Requires-Dist: pytest-asyncio>=0.21.0; extra == 'dev'
Requires-Dist: pytest-cov>=4.0.0; extra == 'dev'
Requires-Dist: pytest>=7.0.0; extra == 'dev'
